plugin/__init__.py
plugin/test_plugin.py
mongeasy_test_plugin-0.0.1.dist-info/METADATA
mongeasy_test_plugin-0.0.1.dist-info/WHEEL
mongeasy_test_plugin-0.0.1.dist-info/top_level.txt
mongeasy_test_plugin-0.0.1.dist-info/RECORD
